nonebot_plugin_aiqqbot/__init__.py
nonebot_plugin_aiqqbot/config.py
nonebot_plugin_aiqqbot/presets/catgirl.txt
nonebot_plugin_aiqqbot/presets/default.txt
nonebot_plugin_aiqqbot/presets/kua.txt
nonebot_plugin_aiqqbot/presets/nvyou.txt
nonebot_plugin_aiqqbot-0.1.10.dist-info/LICENSE
nonebot_plugin_aiqqbot-0.1.10.dist-info/METADATA
nonebot_plugin_aiqqbot-0.1.10.dist-info/WHEEL
nonebot_plugin_aiqqbot-0.1.10.dist-info/RECORD
