Metadata-Version: 2.1
Name: nonebot-plugin-aiqqbot
Version: 0.1.10
Summary: A NoneBot plugin for AI bot
Author: caoshuo2003
Author-email: caoshuo2003@gmail.com
Requires-Python: >=3.9,<4.0
Classifier: Programming Language :: Python :: 3
Classifier: Programming Language :: Python :: 3.9
Classifier: Programming Language :: Python :: 3.10
Classifier: Programming Language :: Python :: 3.11
Classifier: Programming Language :: Python :: 3.12
Requires-Dist: aiocron (>=2.0,<3.0)
Requires-Dist: httpx (==0.27.1)
Requires-Dist: nonebot-adapter-onebot (>=2.0,<3.0)
Requires-Dist: nonebot-plugin-localstore (>=0.7.4,<0.8.0)
Requires-Dist: nonebot2 (>=2.4.1,<3.0.0)
Requires-Dist: openai (>=1.65.4,<2.0.0)
